vicinator/__init__.py
vicinator/vicinator.py
vicinator/tests/__init__.py
vicinator/tests/test_vicinator.py
Vicinator-0.0.32.dist-info/LICENSE
Vicinator-0.0.32.dist-info/METADATA
Vicinator-0.0.32.dist-info/WHEEL
Vicinator-0.0.32.dist-info/entry_points.txt
Vicinator-0.0.32.dist-info/top_level.txt
Vicinator-0.0.32.dist-info/RECORD
