Metadata-Version: 2.1
Name: Vicinator
Version: 0.0.32
Summary: A small python package to trace orthology neighborhood across feature files
Home-page: https://github.com/ba1/vicinator
Author: Ba1
Author-email: djahanschiri@bio.uni-frankfurt.de
License: UNKNOWN
Platform: UNKNOWN
Classifier: Programming Language :: Python :: 3
Classifier: License :: OSI Approved :: MIT License
Classifier: Operating System :: OS Independent
Requires-Python: >=3.6
Requires-Dist: ansi2html (>=1.5.2)
Requires-Dist: colorama (>=0.4.4)
Requires-Dist: ete3 (>=3.1.2)
Requires-Dist: pandas (>=1.1.3)
Requires-Dist: importlib-metadata (>=3.1.1setuptools-scm>=5.0.1)
